googlepatentscraper/__init__.py
googlepatentscraper/document.py
googlepatentscraper-0.2.dist-info/LICENSE
googlepatentscraper-0.2.dist-info/METADATA
googlepatentscraper-0.2.dist-info/WHEEL
googlepatentscraper-0.2.dist-info/top_level.txt
googlepatentscraper-0.2.dist-info/RECORD
