Metadata-Version: 2.1
Name: googlepatentscraper
Version: 0.2
Summary: UNKNOWN
Home-page: https://github.com/linuskohl/googlepatentscraper
Author: Linus Kohl
Author-email: linus@munichresearch.com
License: GPLv3
Platform: UNKNOWN
Requires-Python: >=3.6
Requires-Dist: requests
Requires-Dist: lxml
